{
    "canonical_url": "http://www.getty.edu/art/collection/objects/68908",
    "culture": "American",
    "date": "1870s",
    "description": "York Street - North. [Providence, Rhode Island]; Gardner Blandin (American, active Providence, Rhode Island 1860s - 1870s); 1870s; Albumen silver print; 84.XC.979.200; Gift of Weston J. and Mary M. Naef; J. Paul Getty Museum, Los Angeles, California",
    "image": "http://www.getty.edu/museum/media/images/web/enlarge/07543401.jpg",
    "keywords": "Getty Museum collections, artworks, art works, art history, video, interpretation of art, acquisitions, artists, Getty art, collections Getty, collezioni Getty, colecciones Getty, Sammlung Getty, Getty exhibits, Getty current exhibitions, Getty Museum exhibits, los angeles collections, antiquities, decorative arts, sculpture, manuscripts, photography, paintings, drawings",
    "maker": "Gardner Blandin",
    "medium": "Albumen silver print",
    "name": "York Street - North. [Providence, Rhode Island]",
    "object_number": "84.XC.979.200",
    "object_type": "Stereograph",
    "on_view": "no",
    "open_content": "no",
    "thumbimage": "http://www.getty.edu/museum/media/images/web/thumbnail/07543401.jpg",
    "title": "York Street - North. [Providence, Rhode Island]"
}