{
    "canonical_url": "http://www.getty.edu/art/collection/objects/62535",
    "culture": "American",
    "date": "August 1864",
    "description": "Wharves at City Point, Va. after explosion of ordinance barges.; A.J. Russell (American, 1830 - 1902); City Point, Virginia, United States; August 1864; Albumen silver print; 20.7 x 31.1 cm (8 1/8 x 12 1/4 in.); 84.XP.477.25; J. Paul Getty Museum, Los Angeles, California",
    "dimensions": "20.7 x 31.1 cm (8 1/8 x 12 1/4 in.)",
    "image": "http://www.getty.edu/museum/media/images/web/enlarge/069060B1V1.jpg",
    "keywords": "Getty Museum collections, artworks, art works, art history, video, interpretation of art, acquisitions, artists, Getty art, collections Getty, collezioni Getty, colecciones Getty, Sammlung Getty, Getty exhibits, Getty current exhibitions, Getty Museum exhibits, los angeles collections, antiquities, decorative arts, sculpture, manuscripts, photography, paintings, drawings",
    "maker": "A.J. Russell",
    "medium": "Albumen silver print",
    "name": "Wharves at City Point, Va. after explosion of ordinance barges.",
    "object_number": "84.XP.477.25",
    "object_type": "Print",
    "on_view": "no",
    "open_content": "no",
    "place_created": "City Point, Virginia, United States",
    "thumbimage": "http://www.getty.edu/museum/media/images/web/thumbnail/069060B1V1.jpg",
    "title": "Wharves at City Point, Va. after explosion of ordinance barges."
}