{
    "canonical_url": "http://www.getty.edu/art/collection/objects/62527",
    "culture": "American",
    "date": "July 1863",
    "description": "No. 242. Arsenal, Washington, D.C., North Front. Interior Court. Group of Officers in foreground.; A.J. Russell (American, 1830 - 1902); Washington, District of Columbia, United States; July 1863; Albumen silver print; 26.7 x 37.5 cm (10 1/2 x 14 3/4 in.); 84.XP.477.17; J. Paul Getty Museum, Los Angeles, California",
    "dimensions": "26.7 x 37.5 cm (10 1/2 x 14 3/4 in.)",
    "image": "http://www.getty.edu/museum/media/images/web/enlarge/069052B1V1.jpg",
    "keywords": "Getty Museum collections, artworks, art works, art history, video, interpretation of art, acquisitions, artists, Getty art, collections Getty, collezioni Getty, colecciones Getty, Sammlung Getty, Getty exhibits, Getty current exhibitions, Getty Museum exhibits, los angeles collections, antiquities, decorative arts, sculpture, manuscripts, photography, paintings, drawings",
    "maker": "A.J. Russell",
    "medium": "Albumen silver print",
    "name": "No. 242. Arsenal, Washington, D.C., North Front. Interior Court. Group of Officers in foreground.",
    "object_number": "84.XP.477.17",
    "object_type": "Print",
    "on_view": "no",
    "open_content": "no",
    "place_created": "Washington, District of Columbia, United States",
    "thumbimage": "http://www.getty.edu/museum/media/images/web/thumbnail/069052B1V1.jpg",
    "title": "No. 242. Arsenal, Washington, D.C., North Front. Interior Court. Group of Officers in foreground."
}