{
    "canonical_url": "http://www.getty.edu/art/collection/objects/88",
    "culture": "Swiss",
    "date": "1532 to 1535",
    "description": "Portrait of a Scholar or Cleric; Hans Holbein the Younger (German, 1497/1498 - 1543); 1532 to 1535; Black and red chalk, pen and brush and black ink, on pink prepared paper; 21.9 × 18.4 cm (8 5/8 × 7 1/4 in.); 84.GG.93; J. Paul Getty Museum, Los Angeles, California",
    "dimensions": "21.9 × 18.4 cm (8 5/8 × 7 1/4 in.)",
    "image": "http://www.getty.edu/museum/media/images/web/enlarge/00008801.jpg",
    "image_full": "http://www.getty.edu/museum/media/images/web/download/00008801.jpg",
    "keywords": "Getty Museum collections, artworks, art works, art history, video, interpretation of art, acquisitions, artists, Getty art, collections Getty, collezioni Getty, colecciones Getty, Sammlung Getty, Getty exhibits, Getty current exhibitions, Getty Museum exhibits, los angeles collections, antiquities, decorative arts, sculpture, manuscripts, photography, paintings, drawings",
    "maker": "Hans Holbein the Younger",
    "medium": "Black and red chalk, pen and brush and black ink, on pink prepared paper",
    "name": "Portrait of a Scholar or Cleric",
    "object_number": "84.GG.93",
    "object_type": "Drawing",
    "on_view": "no",
    "open_content": "yes",
    "thumbimage": "http://www.getty.edu/museum/media/images/web/thumbnail/00008801.jpg",
    "title": "Portrait of a Scholar or Cleric"
}