{
    "canonical_url": "http://www.getty.edu/art/collection/objects/38229",
    "culture": "British",
    "date": "September 22-23, 1845",
    "description": "[On Board the HMS Superb]; Attributed to Nikolaas Henneman (British, 1813 - 1893), and Attributed to William Henry Fox Talbot (English, 1800 - 1877); September 22-23, 1845; Salted paper print from a calotype negative; 16.2 x 19.9 cm (6 3/8 x 7 13/16 in.); 84.XP.259.18; J. Paul Getty Museum, Los Angeles, California",
    "dimensions": "16.2 x 19.9 cm (6 3/8 x 7 13/16 in.)",
    "image": "http://www.getty.edu/museum/media/images/web/enlarge/044726B1V1.jpg",
    "keywords": "Getty Museum collections, artworks, art works, art history, video, interpretation of art, acquisitions, artists, Getty art, collections Getty, collezioni Getty, colecciones Getty, Sammlung Getty, Getty exhibits, Getty current exhibitions, Getty Museum exhibits, los angeles collections, antiquities, decorative arts, sculpture, manuscripts, photography, paintings, drawings",
    "maker": "Attributed to Nikolaas Henneman, and Attributed to William Henry Fox Talbot",
    "medium": "Salted paper print from a calotype negative",
    "name": "[On Board the HMS Superb]",
    "object_number": "84.XP.259.18",
    "object_type": "Print",
    "on_view": "no",
    "open_content": "no",
    "thumbimage": "http://www.getty.edu/museum/media/images/web/thumbnail/044726B1V1.jpg",
    "title": "[On Board the HMS Superb]"
}