{
    "canonical_url": "http://www.getty.edu/art/collection/objects/12090",
    "culture": "Greek (Attic)",
    "date": "about 510 B.C.",
    "description": "Attic Red-Figure Cup Type C; Attributed to the Ambrosios Painter (Greek (Attic), active 510 - 500 B.C.); Athens, Greece; about 510 B.C.; Terracotta; 6.5 × 25.1 × 18.9 cm (2 9/16 × 9 7/8 × 7 7/16 in.); 86.AE.298; J. Paul Getty Museum, Los Angeles, California",
    "dimensions": "6.5 × 25.1 × 18.9 cm (2 9/16 × 9 7/8 × 7 7/16 in.)",
    "image": "http://www.getty.edu/museum/media/images/web/enlarge/01417101.jpg",
    "image_full": "http://www.getty.edu/museum/media/images/web/download/01417101.jpg",
    "keywords": "Getty Museum collections, artworks, art works, art history, video, interpretation of art, acquisitions, artists, Getty art, collections Getty, collezioni Getty, colecciones Getty, Sammlung Getty, Getty exhibits, Getty current exhibitions, Getty Museum exhibits, los angeles collections, antiquities, decorative arts, sculpture, manuscripts, photography, paintings, drawings",
    "maker": "Attributed to the Ambrosios Painter",
    "medium": "Terracotta",
    "name": "Attic Red-Figure Cup Type C",
    "object_number": "86.AE.298",
    "object_type": "Cup",
    "on_view": "no",
    "open_content": "yes",
    "place_created": "Athens, Greece",
    "thumbimage": "http://www.getty.edu/museum/media/images/web/thumbnail/01417101.jpg",
    "title": "Attic Red-Figure Cup Type C"
}