{
    "canonical_url": "http://www.getty.edu/art/collection/objects/44035",
    "culture": "British",
    "date": "about 1885 - 1899",
    "description": "[Unidentified older man seated, holding gloves]; Alfred Ellis (British, 1854 - 1930); about 1885 - 1899; Albumen silver print; 14.6 × 10.4 cm (5 3/4 × 4 1/16 in.); 84.XP.769.60; J. Paul Getty Museum, Los Angeles, California",
    "dimensions": "14.6 × 10.4 cm (5 3/4 × 4 1/16 in.)",
    "image": "http://www.getty.edu/museum/media/images/web/enlarge/050541B1V1.jpg",
    "keywords": "Getty Museum collections, artworks, art works, art history, video, interpretation of art, acquisitions, artists, Getty art, collections Getty, collezioni Getty, colecciones Getty, Sammlung Getty, Getty exhibits, Getty current exhibitions, Getty Museum exhibits, los angeles collections, antiquities, decorative arts, sculpture, manuscripts, photography, paintings, drawings",
    "maker": "Alfred Ellis",
    "medium": "Albumen silver print",
    "name": "[Unidentified older man seated, holding gloves]",
    "object_number": "84.XP.769.60",
    "object_type": "Card photograph",
    "on_view": "no",
    "open_content": "no",
    "thumbimage": "http://www.getty.edu/museum/media/images/web/thumbnail/050541B1V1.jpg",
    "title": "[Unidentified older man seated, holding gloves]"
}