{
    "canonical_url": "http://www.getty.edu/art/collection/objects/15232",
    "culture": "Roman",
    "date": "1st century",
    "description": "Lamp; Unknown; North Africa, Tunisia; 1st century; Terracotta; 11 x 4 x 7.6 cm (4 5/16 x 1 9/16 x 3 in.); 80.AQ.46.6; Gift of William L. Eagleton, Jr.; J. Paul Getty Museum, Los Angeles, California",
    "dimensions": "11 x 4 x 7.6 cm (4 5/16 x 1 9/16 x 3 in.)",
    "image": "http://www.getty.edu/museum/media/images/web/enlarge/01869501.jpg",
    "image_full": "http://www.getty.edu/museum/media/images/web/download/01869501.jpg",
    "keywords": "Getty Museum collections, artworks, art works, art history, video, interpretation of art, acquisitions, artists, Getty art, collections Getty, collezioni Getty, colecciones Getty, Sammlung Getty, Getty exhibits, Getty current exhibitions, Getty Museum exhibits, los angeles collections, antiquities, decorative arts, sculpture, manuscripts, photography, paintings, drawings",
    "maker": "Unknown",
    "medium": "Terracotta",
    "name": "Lamp",
    "object_number": "80.AQ.46.6",
    "object_type": "Lamp",
    "on_view": "no",
    "open_content": "yes",
    "place_created": "North Africa, Tunisia",
    "thumbimage": "http://www.getty.edu/museum/media/images/web/thumbnail/01869501.jpg",
    "title": "Lamp"
}