{
    "canonical_url": "http://www.getty.edu/art/collection/objects/41042",
    "culture": "English",
    "date": "1871",
    "description": "Remains, Hall of Columns, Medinet Habou; Francis Frith (English, 1822 - 1898); 1871; Albumen silver print; 16.5 x 21 cm (6 1/2 x 8 1/4 in.); 84.XM.633.21; J. Paul Getty Museum, Los Angeles, California",
    "dimensions": "16.5 x 21 cm (6 1/2 x 8 1/4 in.)",
    "image": "http://www.getty.edu/museum/media/images/web/enlarge/047548B1V1.jpg",
    "keywords": "Getty Museum collections, artworks, art works, art history, video, interpretation of art, acquisitions, artists, Getty art, collections Getty, collezioni Getty, colecciones Getty, Sammlung Getty, Getty exhibits, Getty current exhibitions, Getty Museum exhibits, los angeles collections, antiquities, decorative arts, sculpture, manuscripts, photography, paintings, drawings",
    "maker": "Francis Frith",
    "medium": "Albumen silver print",
    "name": "Remains, Hall of Columns, Medinet Habou",
    "object_number": "84.XM.633.21",
    "object_type": "Print",
    "on_view": "no",
    "open_content": "no",
    "thumbimage": "http://www.getty.edu/museum/media/images/web/thumbnail/047548B1V1.jpg",
    "title": "Remains, Hall of Columns, Medinet Habou"
}