{
    "canonical_url": "http://www.getty.edu/art/collection/objects/48437",
    "culture": "French",
    "date": "about 1870 - 1890",
    "description": "Mena Coach; G. Lekegian (French, active Paris, France and Egypt 1870s - 1890s); Giza, Egypt; about 1870 - 1890; Albumen silver print; 20.9 x 27.3 cm (8 1/4 x 10 3/4 in.); 84.XM.1407.23; J. Paul Getty Museum, Los Angeles, California",
    "dimensions": "20.9 x 27.3 cm (8 1/4 x 10 3/4 in.)",
    "keywords": "Getty Museum collections, artworks, art works, art history, video, interpretation of art, acquisitions, artists, Getty art, collections Getty, collezioni Getty, colecciones Getty, Sammlung Getty, Getty exhibits, Getty current exhibitions, Getty Museum exhibits, los angeles collections, antiquities, decorative arts, sculpture, manuscripts, photography, paintings, drawings",
    "maker": "G. Lekegian",
    "medium": "Albumen silver print",
    "name": "Mena Coach",
    "object_number": "84.XM.1407.23",
    "object_type": "Print",
    "on_view": "no",
    "open_content": "no",
    "place_created": "Giza, Egypt",
    "title": "Mena Coach"
}