{
    "canonical_url": "http://www.getty.edu/art/collection/objects/6269",
    "culture": "French",
    "date": "early 20th century",
    "description": "Vertical stile to retain overdoor panel 84.DH.34.18; tenons at both ends; Unknown; Paris, France; early 20th century; Painted oak; 9 × 190.5 cm (3 9/16 × 75 in.); 84.DH.34.72; J. Paul Getty Museum, Los Angeles, California",
    "dimensions": "9 × 190.5 cm (3 9/16 × 75 in.)",
    "keywords": "Getty Museum collections, artworks, art works, art history, video, interpretation of art, acquisitions, artists, Getty art, collections Getty, collezioni Getty, colecciones Getty, Sammlung Getty, Getty exhibits, Getty current exhibitions, Getty Museum exhibits, los angeles collections, antiquities, decorative arts, sculpture, manuscripts, photography, paintings, drawings",
    "location": "gc",
    "maker": "Unknown",
    "medium": "Painted oak",
    "name": "Vertical stile to retain overdoor panel 84.DH.34.18; tenons at both ends",
    "object_number": "84.DH.34.72",
    "object_type": "Wall paneling, room element",
    "on_view": "yes",
    "open_content": "no",
    "place_created": "Paris, France",
    "title": "Vertical stile to retain overdoor panel 84.DH.34.18; tenons at both ends"
}