{
    "canonical_url": "http://www.getty.edu/art/collection/objects/1277",
    "culture": "Italian",
    "date": "about 1625 - 1635",
    "description": "Tabernacle Door with the Crucifixion; Francesco Mochi (Italian, 1580 - 1654); Italy; about 1625 - 1635; Gilt bronze; 54 x 26 cm (21 1/4 x 10 1/4 in.); 95.SB.2; J. Paul Getty Museum, Los Angeles, California",
    "dimensions": "54 x 26 cm (21 1/4 x 10 1/4 in.)",
    "image": "http://www.getty.edu/museum/media/images/web/enlarge/00148701.jpg",
    "image_full": "http://www.getty.edu/museum/media/images/web/download/00148701.jpg",
    "keywords": "Getty Museum collections, artworks, art works, art history, video, interpretation of art, acquisitions, artists, Getty art, collections Getty, collezioni Getty, colecciones Getty, Sammlung Getty, Getty exhibits, Getty current exhibitions, Getty Museum exhibits, los angeles collections, antiquities, decorative arts, sculpture, manuscripts, photography, paintings, drawings",
    "location": "gc",
    "maker": "Francesco Mochi",
    "medium": "Gilt bronze",
    "name": "Tabernacle Door with the Crucifixion",
    "object_number": "95.SB.2",
    "object_type": "Sculpture",
    "on_view": "yes",
    "open_content": "yes",
    "place_created": "Italy",
    "thumbimage": "http://www.getty.edu/museum/media/images/web/thumbnail/00148701.jpg",
    "title": "Tabernacle Door with the Crucifixion"
}