{
    "canonical_url": "http://www.getty.edu/art/collection/objects/59310",
    "date": "1889 - 1894",
    "description": "A.M.G. (on cover) [Views, group portraits, etc. taken 1889 - 1894, of England and various islands in the Indian Ocean]; A.M.G. (British, active 1880s); 1889 - 1894; Silver bromide; Closed: 37.1 x 54 x 3.4 cm (14 5/8 x 21 1/4 x 1 5/16 in.); 84.XA.698.3.3; J. Paul Getty Museum, Los Angeles, California",
    "dimensions": "Closed: 37.1 x 54 x 3.4 cm (14 5/8 x 21 1/4 x 1 5/16 in.)",
    "keywords": "Getty Museum collections, artworks, art works, art history, video, interpretation of art, acquisitions, artists, Getty art, collections Getty, collezioni Getty, colecciones Getty, Sammlung Getty, Getty exhibits, Getty current exhibitions, Getty Museum exhibits, los angeles collections, antiquities, decorative arts, sculpture, manuscripts, photography, paintings, drawings",
    "maker": "A.M.G.",
    "medium": "Silver bromide",
    "name": "A.M.G. (on cover) [Views, group portraits, etc. taken 1889 - 1894, of England and various islands in the Indian Ocean]",
    "object_number": "84.XA.698.3.3",
    "object_type": "Album",
    "on_view": "no",
    "open_content": "no",
    "title": "A.M.G. (on cover) [Views, group portraits, etc. taken 1889 - 1894, of England and various islands in the Indian Ocean]"
}