{
    "canonical_url": "http://www.getty.edu/art/collection/objects/48988",
    "culture": "French",
    "date": "June 1892",
    "description": "[Portrait of seated girl]; Otto (French, active Paris, France 1890s - 1930s); Paris, France; June 1892; Gelatin silver print; 28.9 × 22.6 cm (11 3/8 × 8 7/8 in.); 84.XP.1440.2; J. Paul Getty Museum, Los Angeles, California",
    "dimensions": "28.9 × 22.6 cm (11 3/8 × 8 7/8 in.)",
    "keywords": "Getty Museum collections, artworks, art works, art history, video, interpretation of art, acquisitions, artists, Getty art, collections Getty, collezioni Getty, colecciones Getty, Sammlung Getty, Getty exhibits, Getty current exhibitions, Getty Museum exhibits, los angeles collections, antiquities, decorative arts, sculpture, manuscripts, photography, paintings, drawings",
    "maker": "Otto",
    "medium": "Gelatin silver print",
    "name": "[Portrait of seated girl]",
    "object_number": "84.XP.1440.2",
    "object_type": "Print",
    "on_view": "no",
    "open_content": "no",
    "place_created": "Paris, France",
    "title": "[Portrait of seated girl]"
}