{
    "canonical_url": "http://www.getty.edu/art/collection/objects/46345",
    "culture": "American",
    "date": "1948",
    "description": "[Faulkner Country: Probably a Tenant Farmer's House]; Walker Evans (American, 1903 - 1975); 1948; Gelatin silver print; 5.7 x 8.9 cm (2 1/4 x 3 1/2 in.); 84.XM.956.1020; J. Paul Getty Museum, Los Angeles, California",
    "dimensions": "5.7 x 8.9 cm (2 1/4 x 3 1/2 in.)",
    "image": "http://www.getty.edu/museum/media/images/web/enlarge/052851B1V1.jpg",
    "keywords": "Getty Museum collections, artworks, art works, art history, video, interpretation of art, acquisitions, artists, Getty art, collections Getty, collezioni Getty, colecciones Getty, Sammlung Getty, Getty exhibits, Getty current exhibitions, Getty Museum exhibits, los angeles collections, antiquities, decorative arts, sculpture, manuscripts, photography, paintings, drawings",
    "maker": "Walker Evans",
    "medium": "Gelatin silver print",
    "name": "[Faulkner Country: Probably a Tenant Farmer's House]",
    "object_number": "84.XM.956.1020",
    "object_type": "Print",
    "on_view": "no",
    "open_content": "no",
    "thumbimage": "http://www.getty.edu/museum/media/images/web/thumbnail/052851B1V1.jpg",
    "title": "[Faulkner Country: Probably a Tenant Farmer's House]"
}