{
    "canonical_url": "http://www.getty.edu/art/collection/objects/43333",
    "culture": "French",
    "date": "mid - late 19th century",
    "description": "[Dogs]; Léon Crémière (French, 1831 - after 1882); mid - late 19th century; Albumen silver print; 13.3 × 19.8 cm (5 1/4 × 7 13/16 in.); 84.XP.720.53; J. Paul Getty Museum, Los Angeles, California",
    "dimensions": "13.3 × 19.8 cm (5 1/4 × 7 13/16 in.)",
    "image": "http://www.getty.edu/museum/media/images/web/enlarge/04983901.jpg",
    "image_full": "http://www.getty.edu/museum/media/images/web/download/04983901.jpg",
    "keywords": "Getty Museum collections, artworks, art works, art history, video, interpretation of art, acquisitions, artists, Getty art, collections Getty, collezioni Getty, colecciones Getty, Sammlung Getty, Getty exhibits, Getty current exhibitions, Getty Museum exhibits, los angeles collections, antiquities, decorative arts, sculpture, manuscripts, photography, paintings, drawings",
    "maker": "Léon Crémière",
    "medium": "Albumen silver print",
    "name": "[Dogs]",
    "object_number": "84.XP.720.53",
    "object_type": "Print",
    "on_view": "no",
    "open_content": "yes",
    "thumbimage": "http://www.getty.edu/museum/media/images/web/thumbnail/04983901.jpg",
    "title": "[Dogs]"
}