{
    "canonical_url": "http://www.getty.edu/art/collection/objects/29658",
    "culture": "Cycladic",
    "date": "2600 - 2500 B.C.",
    "description": "Head of a Figure of the Early Spedos Variety; Unknown; Cyclades, Greece; 2600 - 2500 B.C.; Marble with traces of polychromy; 22.8 × 8.9 × 6.4 cm (9 × 3 1/2 × 2 1/2 in.); 96.AA.27; J. Paul Getty Museum, Los Angeles, California",
    "dimensions": "22.8 × 8.9 × 6.4 cm (9 × 3 1/2 × 2 1/2 in.)",
    "image": "http://www.getty.edu/museum/media/images/web/enlarge/03561201.jpg",
    "image_full": "http://www.getty.edu/museum/media/images/web/download/03561201.jpg",
    "keywords": "Getty Museum collections, artworks, art works, art history, video, interpretation of art, acquisitions, artists, Getty art, collections Getty, collezioni Getty, colecciones Getty, Sammlung Getty, Getty exhibits, Getty current exhibitions, Getty Museum exhibits, los angeles collections, antiquities, decorative arts, sculpture, manuscripts, photography, paintings, drawings",
    "maker": "Unknown",
    "medium": "Marble with traces of polychromy",
    "name": "Head of a Figure of the Early Spedos Variety",
    "object_number": "96.AA.27",
    "object_type": "Statues",
    "on_view": "no",
    "open_content": "yes",
    "place_created": "Cyclades, Greece",
    "thumbimage": "http://www.getty.edu/museum/media/images/web/thumbnail/03561201.jpg",
    "title": "Head of a Figure of the Early Spedos Variety"
}