{
    "canonical_url": "http://www.getty.edu/art/collection/objects/50232",
    "culture": "American",
    "date": "about 1872",
    "description": "Nevada fall / 700 feet / 8243\"; Thomas Houseworth (American, 1829 - 1915); about 1872; Albumen silver print; 21.3 x 16.2 cm (8 3/8 x 6 3/8 in.); 85.XP.8.17; J. Paul Getty Museum, Los Angeles, California",
    "dimensions": "21.3 x 16.2 cm (8 3/8 x 6 3/8 in.)",
    "image": "http://www.getty.edu/museum/media/images/web/enlarge/056739B1V1.jpg",
    "keywords": "Getty Museum collections, artworks, art works, art history, video, interpretation of art, acquisitions, artists, Getty art, collections Getty, collezioni Getty, colecciones Getty, Sammlung Getty, Getty exhibits, Getty current exhibitions, Getty Museum exhibits, los angeles collections, antiquities, decorative arts, sculpture, manuscripts, photography, paintings, drawings",
    "maker": "Thomas Houseworth",
    "medium": "Albumen silver print",
    "name": "Nevada fall / 700 feet / 8243\"",
    "object_number": "85.XP.8.17",
    "object_type": "Print",
    "on_view": "no",
    "open_content": "no",
    "thumbimage": "http://www.getty.edu/museum/media/images/web/thumbnail/056739B1V1.jpg",
    "title": "Nevada fall / 700 feet / 8243\""
}