{
    "canonical_url": "http://www.getty.edu/art/collection/objects/64397",
    "culture": "Dutch",
    "date": "about  1870 - 1890",
    "description": "[Landscape with cows and windmills]; Unknown maker, Dutch; about  1870 - 1890; Albumen silver print; 11.2 × 18.4 cm (4 7/16 × 7 1/4 in.); 84.XP.1430.38; J. Paul Getty Museum, Los Angeles, California",
    "dimensions": "11.2 × 18.4 cm (4 7/16 × 7 1/4 in.)",
    "image": "http://www.getty.edu/museum/media/images/web/enlarge/070923B1V1.jpg",
    "keywords": "Getty Museum collections, artworks, art works, art history, video, interpretation of art, acquisitions, artists, Getty art, collections Getty, collezioni Getty, colecciones Getty, Sammlung Getty, Getty exhibits, Getty current exhibitions, Getty Museum exhibits, los angeles collections, antiquities, decorative arts, sculpture, manuscripts, photography, paintings, drawings",
    "maker": "Unknown maker, Dutch",
    "medium": "Albumen silver print",
    "name": "[Landscape with cows and windmills]",
    "object_number": "84.XP.1430.38",
    "object_type": "Print",
    "on_view": "no",
    "open_content": "no",
    "thumbimage": "http://www.getty.edu/museum/media/images/web/thumbnail/070923B1V1.jpg",
    "title": "[Landscape with cows and windmills]"
}