{
    "canonical_url": "http://www.getty.edu/art/collection/objects/41597",
    "culture": "American",
    "date": "1940",
    "description": "Carole Landis; Don English (American, 1901 - 1964); Beverly Hills, California, United States; 1940; Gelatin silver print; 31.5 x 24.5 cm (12 3/8 x 9 5/8 in.); 84.XP.684.31; J. Paul Getty Museum, Los Angeles, California",
    "dimensions": "31.5 x 24.5 cm (12 3/8 x 9 5/8 in.)",
    "keywords": "Getty Museum collections, artworks, art works, art history, video, interpretation of art, acquisitions, artists, Getty art, collections Getty, collezioni Getty, colecciones Getty, Sammlung Getty, Getty exhibits, Getty current exhibitions, Getty Museum exhibits, los angeles collections, antiquities, decorative arts, sculpture, manuscripts, photography, paintings, drawings",
    "maker": "Don English",
    "medium": "Gelatin silver print",
    "name": "Carole Landis",
    "object_number": "84.XP.684.31",
    "object_type": "Print",
    "on_view": "no",
    "open_content": "no",
    "place_created": "Beverly Hills, California, United States",
    "thumbimage": "http://www.getty.edu/museum/media/images/web/thumbnail/048103B1V1.jpg",
    "title": "Carole Landis"
}