{
    "canonical_url": "http://www.getty.edu/art/collection/objects/36023",
    "culture": "American",
    "date": "1933 - 1938",
    "description": "[Bois de Boulogne].; Lisette Model (American, born Austria, 1901 - 1983); 1933 - 1938; Gelatin silver print; 34.6 x 27.1 cm (13 5/8 x 10 11/16 in.); 84.XM.153.79; J. Paul Getty Museum, Los Angeles, California",
    "dimensions": "34.6 x 27.1 cm (13 5/8 x 10 11/16 in.)",
    "image": "http://www.getty.edu/museum/media/images/web/enlarge/04252001.jpg",
    "keywords": "Getty Museum collections, artworks, art works, art history, video, interpretation of art, acquisitions, artists, Getty art, collections Getty, collezioni Getty, colecciones Getty, Sammlung Getty, Getty exhibits, Getty current exhibitions, Getty Museum exhibits, los angeles collections, antiquities, decorative arts, sculpture, manuscripts, photography, paintings, drawings",
    "maker": "Lisette Model",
    "medium": "Gelatin silver print",
    "name": "[Bois de Boulogne].",
    "object_number": "84.XM.153.79",
    "object_type": "Print",
    "on_view": "no",
    "open_content": "no",
    "thumbimage": "http://www.getty.edu/museum/media/images/web/thumbnail/04252001.jpg",
    "title": "[Bois de Boulogne]."
}