{
    "canonical_url": "http://www.getty.edu/art/collection/objects/42358",
    "culture": "Italian",
    "date": "about 1880 - 1900",
    "description": "Firenze - Galleria Pitti - Interno della sala dell'Iliade: Pietro da Cortona; Carlo Brogi (Italian, 1850 - 1925); Florence, Italy; about 1880 - 1900; Albumen silver print; 18.5 × 24.9 cm (7 5/16 × 9 13/16 in.); 84.XP.709.409; J. Paul Getty Museum, Los Angeles, California",
    "dimensions": "18.5 × 24.9 cm (7 5/16 × 9 13/16 in.)",
    "image": "http://www.getty.edu/museum/media/images/web/enlarge/048864B1V1.jpg",
    "keywords": "Getty Museum collections, artworks, art works, art history, video, interpretation of art, acquisitions, artists, Getty art, collections Getty, collezioni Getty, colecciones Getty, Sammlung Getty, Getty exhibits, Getty current exhibitions, Getty Museum exhibits, los angeles collections, antiquities, decorative arts, sculpture, manuscripts, photography, paintings, drawings",
    "maker": "Carlo Brogi",
    "medium": "Albumen silver print",
    "name": "Firenze - Galleria Pitti - Interno della sala dell'Iliade: Pietro da Cortona",
    "object_number": "84.XP.709.409",
    "object_type": "Print",
    "on_view": "no",
    "open_content": "no",
    "place_created": "Florence, Italy",
    "thumbimage": "http://www.getty.edu/museum/media/images/web/thumbnail/048864B1V1.jpg",
    "title": "Firenze - Galleria Pitti - Interno della sala dell'Iliade: Pietro da Cortona"
}