{
    "canonical_url": "http://www.getty.edu/art/collection/objects/42361",
    "culture": "Italian",
    "date": "about 1900 - 1920",
    "description": "Palermo - Rosone sulla porta maggiore della Chiesa di S. Agostino; Carlo Brogi (Italian, 1850 - 1925); Palermo, Italy; about 1900 - 1920; Gelatin silver print; 24.3 × 19.7 cm (9 9/16 × 7 3/4 in.); 84.XP.709.412; J. Paul Getty Museum, Los Angeles, California",
    "dimensions": "24.3 × 19.7 cm (9 9/16 × 7 3/4 in.)",
    "image": "http://www.getty.edu/museum/media/images/web/enlarge/048867B1V1.jpg",
    "keywords": "Getty Museum collections, artworks, art works, art history, video, interpretation of art, acquisitions, artists, Getty art, collections Getty, collezioni Getty, colecciones Getty, Sammlung Getty, Getty exhibits, Getty current exhibitions, Getty Museum exhibits, los angeles collections, antiquities, decorative arts, sculpture, manuscripts, photography, paintings, drawings",
    "maker": "Carlo Brogi",
    "medium": "Gelatin silver print",
    "name": "Palermo - Rosone sulla porta maggiore della Chiesa di S. Agostino",
    "object_number": "84.XP.709.412",
    "object_type": "Print",
    "on_view": "no",
    "open_content": "no",
    "place_created": "Palermo, Italy",
    "thumbimage": "http://www.getty.edu/museum/media/images/web/thumbnail/048867B1V1.jpg",
    "title": "Palermo - Rosone sulla porta maggiore della Chiesa di S. Agostino"
}