{
    "canonical_url": "http://www.getty.edu/art/collection/objects/6501",
    "culture": "Modern",
    "date": "20th century",
    "description": "Modern Imitation of a Statuette of a Crouching Aphrodite; Unknown; Europe (?); 20th century; Terracotta with traces of polychromy; 22.2 cm (8 3/4 in.); 57.AD.9; J. Paul Getty Museum, Los Angeles, California",
    "dimensions": "22.2 cm (8 3/4 in.)",
    "image": "http://www.getty.edu/museum/media/images/web/enlarge/00758701.jpg",
    "image_full": "http://www.getty.edu/museum/media/images/web/download/00758701.jpg",
    "keywords": "Getty Museum collections, artworks, art works, art history, video, interpretation of art, acquisitions, artists, Getty art, collections Getty, collezioni Getty, colecciones Getty, Sammlung Getty, Getty exhibits, Getty current exhibitions, Getty Museum exhibits, los angeles collections, antiquities, decorative arts, sculpture, manuscripts, photography, paintings, drawings",
    "maker": "Unknown",
    "medium": "Terracotta with traces of polychromy",
    "name": "Modern Imitation of a Statuette of a Crouching Aphrodite",
    "object_number": "57.AD.9",
    "object_type": "Mythological figure",
    "on_view": "no",
    "open_content": "yes",
    "place_created": "Europe (?)",
    "thumbimage": "http://www.getty.edu/museum/media/images/web/thumbnail/00758701.jpg",
    "title": "Modern Imitation of a Statuette of a Crouching Aphrodite"
}