{
    "canonical_url": "http://www.getty.edu/art/collection/objects/60948",
    "date": "1894",
    "description": "Rip Van Winkle. Illustrated by Frank T. Merrill.; Washington Irving, Frank T. Merrill (American, active 1880s - 1890s); Boston, Massachusetts, United States; 1894; Photogravure; Closed: 22.9 x 17.8 x 1.7 cm (9 x 7 x 11/16 in.); 84.XB.887.12; J. Paul Getty Museum, Los Angeles, California",
    "dimensions": "Closed: 22.9 x 17.8 x 1.7 cm (9 x 7 x 11/16 in.)",
    "keywords": "Getty Museum collections, artworks, art works, art history, video, interpretation of art, acquisitions, artists, Getty art, collections Getty, collezioni Getty, colecciones Getty, Sammlung Getty, Getty exhibits, Getty current exhibitions, Getty Museum exhibits, los angeles collections, antiquities, decorative arts, sculpture, manuscripts, photography, paintings, drawings",
    "maker": "Washington Irving, Frank T. Merrill",
    "medium": "Photogravure",
    "name": "Rip Van Winkle. Illustrated by Frank T. Merrill.",
    "object_number": "84.XB.887.12",
    "object_type": "Book",
    "on_view": "no",
    "open_content": "no",
    "place_created": "Boston, Massachusetts, United States",
    "title": "Rip Van Winkle. Illustrated by Frank T. Merrill."
}