{
    "canonical_url": "http://www.getty.edu/art/collection/objects/45181",
    "culture": "British",
    "date": "1862 - 1872",
    "description": "Ningpo Pagoda; John Thomson (Scottish, 1837 - 1921); Ningbo, China; 1862 - 1872; Albumen silver print; 21 × 15.9 cm (8 1/4 × 6 1/4 in.); 84.XM.859.11; J. Paul Getty Museum, Los Angeles, California",
    "dimensions": "21 × 15.9 cm (8 1/4 × 6 1/4 in.)",
    "keywords": "Getty Museum collections, artworks, art works, art history, video, interpretation of art, acquisitions, artists, Getty art, collections Getty, collezioni Getty, colecciones Getty, Sammlung Getty, Getty exhibits, Getty current exhibitions, Getty Museum exhibits, los angeles collections, antiquities, decorative arts, sculpture, manuscripts, photography, paintings, drawings",
    "maker": "John Thomson",
    "medium": "Albumen silver print",
    "name": "Ningpo Pagoda",
    "object_number": "84.XM.859.11",
    "object_type": "Print",
    "on_view": "no",
    "open_content": "no",
    "place_created": "Ningbo, China",
    "title": "Ningpo Pagoda"
}