{
    "canonical_url": "http://www.getty.edu/art/collection/objects/40173",
    "culture": "American",
    "date": "about 1862 - 1863",
    "description": "Light House, Tybee Island, Georgia; Henry P. Moore (American, 1835 - 1911); Tybee Island, Georgia, United States; about 1862 - 1863; Albumen silver print; 13.1 × 21.1 cm (5 3/16 × 8 5/16 in.); 84.XM.483.2; J. Paul Getty Museum, Los Angeles, California",
    "dimensions": "13.1 × 21.1 cm (5 3/16 × 8 5/16 in.)",
    "image": "http://www.getty.edu/museum/media/images/web/enlarge/046679B1V1.jpg",
    "keywords": "Getty Museum collections, artworks, art works, art history, video, interpretation of art, acquisitions, artists, Getty art, collections Getty, collezioni Getty, colecciones Getty, Sammlung Getty, Getty exhibits, Getty current exhibitions, Getty Museum exhibits, los angeles collections, antiquities, decorative arts, sculpture, manuscripts, photography, paintings, drawings",
    "maker": "Henry P. Moore",
    "medium": "Albumen silver print",
    "name": "Light House, Tybee Island, Georgia",
    "object_number": "84.XM.483.2",
    "object_type": "Print",
    "on_view": "no",
    "open_content": "no",
    "place_created": "Tybee Island, Georgia, United States",
    "thumbimage": "http://www.getty.edu/museum/media/images/web/thumbnail/046679B1V1.jpg",
    "title": "Light House, Tybee Island, Georgia"
}