{
    "canonical_url": "http://www.getty.edu/art/collection/objects/62878",
    "culture": "English",
    "date": "1855; published April 5, 1856",
    "description": "Col. Dickson, R.E.; Roger Fenton (English, 1819 - 1869); 1855; published April 5, 1856; 15.9 x 15.7 cm (6 1/4 x 6 3/16 in.); 84.XO.1266.29; J. Paul Getty Museum, Los Angeles, California",
    "dimensions": "15.9 x 15.7 cm (6 1/4 x 6 3/16 in.)",
    "keywords": "Getty Museum collections, artworks, art works, art history, video, interpretation of art, acquisitions, artists, Getty art, collections Getty, collezioni Getty, colecciones Getty, Sammlung Getty, Getty exhibits, Getty current exhibitions, Getty Museum exhibits, los angeles collections, antiquities, decorative arts, sculpture, manuscripts, photography, paintings, drawings",
    "maker": "Roger Fenton",
    "name": "Col. Dickson, R.E.",
    "object_number": "84.XO.1266.29",
    "object_type": "Print",
    "on_view": "no",
    "open_content": "no",
    "title": "Col. Dickson, R.E."
}