{
    "canonical_url": "http://www.getty.edu/art/collection/objects/45061",
    "culture": "American",
    "date": "about 1860",
    "description": "[Postmortem portrait of an unidentified man]; Unknown maker, American; about 1860; Daguerreotype; 4.9 x 6.2 cm (1 15/16 x 2 7/16 in.); 84.XT.837.20; J. Paul Getty Museum, Los Angeles, California",
    "dimensions": "4.9 x 6.2 cm (1 15/16 x 2 7/16 in.)",
    "keywords": "Getty Museum collections, artworks, art works, art history, video, interpretation of art, acquisitions, artists, Getty art, collections Getty, collezioni Getty, colecciones Getty, Sammlung Getty, Getty exhibits, Getty current exhibitions, Getty Museum exhibits, los angeles collections, antiquities, decorative arts, sculpture, manuscripts, photography, paintings, drawings",
    "maker": "Unknown maker, American",
    "medium": "Daguerreotype",
    "name": "[Postmortem portrait of an unidentified man]",
    "object_number": "84.XT.837.20",
    "object_type": "Cased object",
    "on_view": "no",
    "open_content": "no",
    "title": "[Postmortem portrait of an unidentified man]"
}