{
    "canonical_url": "http://www.getty.edu/art/collection/objects/43880",
    "culture": "American",
    "date": "1977",
    "description": "West Dummerston, Vermont; Susan Barron (American, born 1947); West Dummerston, Vermont, United States; 1977; Gelatin silver print; 9 x 7.8 cm (3 9/16 x 3 1/16 in.); 84.XP.753.44; J. Paul Getty Museum, Los Angeles, California",
    "dimensions": "9 x 7.8 cm (3 9/16 x 3 1/16 in.)",
    "keywords": "Getty Museum collections, artworks, art works, art history, video, interpretation of art, acquisitions, artists, Getty art, collections Getty, collezioni Getty, colecciones Getty, Sammlung Getty, Getty exhibits, Getty current exhibitions, Getty Museum exhibits, los angeles collections, antiquities, decorative arts, sculpture, manuscripts, photography, paintings, drawings",
    "maker": "Susan Barron",
    "medium": "Gelatin silver print",
    "name": "West Dummerston, Vermont",
    "object_number": "84.XP.753.44",
    "object_type": "Print",
    "on_view": "no",
    "open_content": "no",
    "place_created": "West Dummerston, Vermont, United States",
    "thumbimage": "http://www.getty.edu/museum/media/images/web/thumbnail/050386B1V1.jpg",
    "title": "West Dummerston, Vermont"
}