{
    "canonical_url": "http://www.getty.edu/art/collection/objects/57675",
    "culture": "German",
    "date": "about 1924 - 1925",
    "description": "[Schawinsky's Circus, Bauhaus Fest, Weimar]; Eckner Atelier (Germany, active Weimar, Germany); about 1924 - 1925; Gelatin silver print; 13.9 x 8.7 cm (5 1/2 x 3 7/16 in.); 85.XP.260.46; J. Paul Getty Museum, Los Angeles, California",
    "dimensions": "13.9 x 8.7 cm (5 1/2 x 3 7/16 in.)",
    "image": "http://www.getty.edu/museum/media/images/web/enlarge/06418501.jpg",
    "keywords": "Getty Museum collections, artworks, art works, art history, video, interpretation of art, acquisitions, artists, Getty art, collections Getty, collezioni Getty, colecciones Getty, Sammlung Getty, Getty exhibits, Getty current exhibitions, Getty Museum exhibits, los angeles collections, antiquities, decorative arts, sculpture, manuscripts, photography, paintings, drawings",
    "maker": "Eckner Atelier",
    "medium": "Gelatin silver print",
    "name": "[Schawinsky's Circus, Bauhaus Fest, Weimar]",
    "object_number": "85.XP.260.46",
    "object_type": "Card photograph",
    "on_view": "no",
    "open_content": "no",
    "thumbimage": "http://www.getty.edu/museum/media/images/web/thumbnail/06418501.jpg",
    "title": "[Schawinsky's Circus, Bauhaus Fest, Weimar]"
}