{
    "canonical_url": "http://www.getty.edu/art/collection/objects/61673",
    "date": "1885",
    "description": "Lectures, Essays and Published Articles on Scientific and Literary Subjects and on Foreign Travel.; C.C. Merriman, Lewis Company, W.W. Walmsley (American, active 1880s), et al; Rochester, New York, United States; 1885; Heliotype, by Gelatine process; 84.XL.944.7; J. Paul Getty Museum, Los Angeles, California",
    "keywords": "Getty Museum collections, artworks, art works, art history, video, interpretation of art, acquisitions, artists, Getty art, collections Getty, collezioni Getty, colecciones Getty, Sammlung Getty, Getty exhibits, Getty current exhibitions, Getty Museum exhibits, los angeles collections, antiquities, decorative arts, sculpture, manuscripts, photography, paintings, drawings",
    "maker": "C.C. Merriman, Lewis Company, W.W. Walmsley, et al",
    "medium": "Heliotype, by Gelatine process",
    "name": "Lectures, Essays and Published Articles on Scientific and Literary Subjects and on Foreign Travel.",
    "object_number": "84.XL.944.7",
    "object_type": "Book",
    "on_view": "no",
    "open_content": "no",
    "place_created": "Rochester, New York, United States",
    "title": "Lectures, Essays and Published Articles on Scientific and Literary Subjects and on Foreign Travel."
}