{
    "canonical_url": "http://www.getty.edu/art/collection/objects/64127",
    "culture": "French",
    "date": "about 1875",
    "description": "Cap Bernard. Riviere de St. Denis. Reunion.; F. Delisby (French, active 1870s); France; about 1875; Albumen silver print; 10.1 x 16.5 cm (4 x 6 1/2 in.); 84.XP.739.342; J. Paul Getty Museum, Los Angeles, California",
    "dimensions": "10.1 x 16.5 cm (4 x 6 1/2 in.)",
    "image": "http://www.getty.edu/museum/media/images/web/enlarge/070652B1V1.jpg",
    "keywords": "Getty Museum collections, artworks, art works, art history, video, interpretation of art, acquisitions, artists, Getty art, collections Getty, collezioni Getty, colecciones Getty, Sammlung Getty, Getty exhibits, Getty current exhibitions, Getty Museum exhibits, los angeles collections, antiquities, decorative arts, sculpture, manuscripts, photography, paintings, drawings",
    "maker": "F. Delisby",
    "medium": "Albumen silver print",
    "name": "Cap Bernard. Riviere de St. Denis. Reunion.",
    "object_number": "84.XP.739.342",
    "object_type": "Print",
    "on_view": "no",
    "open_content": "no",
    "place_created": "France",
    "thumbimage": "http://www.getty.edu/museum/media/images/web/thumbnail/070652B1V1.jpg",
    "title": "Cap Bernard. Riviere de St. Denis. Reunion."
}