{
    "canonical_url": "http://www.getty.edu/art/collection/objects/39042",
    "culture": "French",
    "date": "1853 - 1854",
    "description": "Jules Janin; Nadar [Gaspard Félix Tournachon] (French, 1820 - 1910); 1853 - 1854; salted paper prints from glass negative; 24.7 × 18.4 cm (9 3/4 × 7 1/4 in.); 84.XM.436.29; J. Paul Getty Museum, Los Angeles, California",
    "dimensions": "24.7 × 18.4 cm (9 3/4 × 7 1/4 in.)",
    "image": "http://www.getty.edu/museum/media/images/web/enlarge/04554801.jpg",
    "image_full": "http://www.getty.edu/museum/media/images/web/download/04554801.jpg",
    "keywords": "Getty Museum collections, artworks, art works, art history, video, interpretation of art, acquisitions, artists, Getty art, collections Getty, collezioni Getty, colecciones Getty, Sammlung Getty, Getty exhibits, Getty current exhibitions, Getty Museum exhibits, los angeles collections, antiquities, decorative arts, sculpture, manuscripts, photography, paintings, drawings",
    "maker": "Nadar [Gaspard Félix Tournachon]",
    "medium": "salted paper prints from glass negative",
    "name": "Jules Janin",
    "object_number": "84.XM.436.29",
    "object_type": "Print",
    "on_view": "no",
    "open_content": "yes",
    "thumbimage": "http://www.getty.edu/museum/media/images/web/thumbnail/04554801.jpg",
    "title": "Jules Janin"
}