{
    "canonical_url": "http://www.getty.edu/art/collection/objects/5668",
    "culture": "Chinese (Kangxi)",
    "date": "porcelain about 1690 - 1700; mounts about 1765 - 1770",
    "description": "Lidded Pot; Unknown; Paris, France; porcelain about 1690 - 1700; mounts about 1765 - 1770; Hard-paste porcelain (blanc de chine); gilt bronze mounts; 25.1 x 18.7 x 15.9 cm (9 7/8 x 7 3/8 x 6 1/4 in.); 78.DI.359; J. Paul Getty Museum, Los Angeles, California",
    "dimensions": "25.1 x 18.7 x 15.9 cm (9 7/8 x 7 3/8 x 6 1/4 in.)",
    "image": "http://www.getty.edu/museum/media/images/web/enlarge/00652501.jpg",
    "image_full": "http://www.getty.edu/museum/media/images/web/download/00652501.jpg",
    "keywords": "Getty Museum collections, artworks, art works, art history, video, interpretation of art, acquisitions, artists, Getty art, collections Getty, collezioni Getty, colecciones Getty, Sammlung Getty, Getty exhibits, Getty current exhibitions, Getty Museum exhibits, los angeles collections, antiquities, decorative arts, sculpture, manuscripts, photography, paintings, drawings",
    "location": "gc",
    "maker": "Unknown",
    "medium": "Hard-paste porcelain (blanc de chine); gilt bronze mounts",
    "name": "Lidded Pot",
    "object_number": "78.DI.359",
    "object_type": "Vase",
    "on_view": "yes",
    "open_content": "yes",
    "place_created": "Paris, France",
    "thumbimage": "http://www.getty.edu/museum/media/images/web/thumbnail/00652501.jpg",
    "title": "Lidded Pot"
}