{
    "canonical_url": "http://www.getty.edu/art/collection/objects/47904",
    "culture": "Belgian",
    "date": "about 1885 - 1895",
    "description": "Gand - St. Bavon; Unknown maker, Belgian; Ghent, Belgium; about 1885 - 1895; Albumen silver print; 16.4 × 10.9 cm (6 7/16 × 4 5/16 in.); 84.XP.1156.10; J. Paul Getty Museum, Los Angeles, California",
    "dimensions": "16.4 × 10.9 cm (6 7/16 × 4 5/16 in.)",
    "image": "http://www.getty.edu/museum/media/images/web/enlarge/054410B1V1.jpg",
    "keywords": "Getty Museum collections, artworks, art works, art history, video, interpretation of art, acquisitions, artists, Getty art, collections Getty, collezioni Getty, colecciones Getty, Sammlung Getty, Getty exhibits, Getty current exhibitions, Getty Museum exhibits, los angeles collections, antiquities, decorative arts, sculpture, manuscripts, photography, paintings, drawings",
    "maker": "Unknown maker, Belgian",
    "medium": "Albumen silver print",
    "name": "Gand - St. Bavon",
    "object_number": "84.XP.1156.10",
    "object_type": "Print",
    "on_view": "no",
    "open_content": "no",
    "place_created": "Ghent, Belgium",
    "thumbimage": "http://www.getty.edu/museum/media/images/web/thumbnail/054410B1V1.jpg",
    "title": "Gand - St. Bavon"
}