{
    "canonical_url": "http://www.getty.edu/art/collection/objects/9820",
    "culture": "South Italian (Canosan)",
    "date": "3rd century B.C.",
    "description": "Canosan Head Vase; Unknown; Canosa, South Italy; 3rd century B.C.; Terracotta and polychromy; 37.2 × 9.2 cm (14 5/8 × 3 5/8 in.); 81.AE.157; Gift of Robert Blaugrund; J. Paul Getty Museum, Los Angeles, California",
    "dimensions": "37.2 × 9.2 cm (14 5/8 × 3 5/8 in.)",
    "keywords": "Getty Museum collections, artworks, art works, art history, video, interpretation of art, acquisitions, artists, Getty art, collections Getty, collezioni Getty, colecciones Getty, Sammlung Getty, Getty exhibits, Getty current exhibitions, Getty Museum exhibits, los angeles collections, antiquities, decorative arts, sculpture, manuscripts, photography, paintings, drawings",
    "maker": "Unknown",
    "medium": "Terracotta and polychromy",
    "name": "Canosan Head Vase",
    "object_number": "81.AE.157",
    "object_type": "Plastic vase",
    "on_view": "no",
    "open_content": "no",
    "place_created": "Canosa, South Italy",
    "title": "Canosan Head Vase"
}