{
    "canonical_url": "http://www.getty.edu/art/collection/objects/59778",
    "culture": "French",
    "date": "1853",
    "description": "Chants et Chansons de la Boheme. Illustres de 26 jolis dessins par Nadar.; Pierre Bry, Original work by Nadar [Gaspard Félix Tournachon] (French, 1820 - 1910); Paris, France; 1853; Engraving; Closed: 16.7 x 10.9 x 1 cm (6 9/16 x 4 5/16 x 3/8 in.); 84.XB.759.15; J. Paul Getty Museum, Los Angeles, California",
    "dimensions": "Closed: 16.7 x 10.9 x 1 cm (6 9/16 x 4 5/16 x 3/8 in.)",
    "keywords": "Getty Museum collections, artworks, art works, art history, video, interpretation of art, acquisitions, artists, Getty art, collections Getty, collezioni Getty, colecciones Getty, Sammlung Getty, Getty exhibits, Getty current exhibitions, Getty Museum exhibits, los angeles collections, antiquities, decorative arts, sculpture, manuscripts, photography, paintings, drawings",
    "maker": "Pierre Bry, Original work by Nadar [Gaspard Félix Tournachon]",
    "medium": "Engraving",
    "name": "Chants et Chansons de la Boheme. Illustres de 26 jolis dessins par Nadar.",
    "object_number": "84.XB.759.15",
    "object_type": "Book",
    "on_view": "no",
    "open_content": "no",
    "place_created": "Paris, France",
    "title": "Chants et Chansons de la Boheme. Illustres de 26 jolis dessins par Nadar."
}