{
    "canonical_url": "http://www.getty.edu/art/collection/objects/366",
    "culture": "Italian",
    "date": "about 1582 - 1585",
    "description": "Kneeling Figure (recto); Reclining Figure (verso); Agostino Carracci (Italian, 1557 - 1602); Italy; about 1582 - 1585; Black chalk with white chalk highlights on blue paper (recto); black chalk on blue paper (verso); 42.1 × 26.8 cm (16 9/16 × 10 9/16 in.); 91.GB.68; J. Paul Getty Museum, Los Angeles, California",
    "dimensions": "42.1 × 26.8 cm (16 9/16 × 10 9/16 in.)",
    "image": "http://www.getty.edu/museum/media/images/web/enlarge/00036901.jpg",
    "image_full": "http://www.getty.edu/museum/media/images/web/download/00036901.jpg",
    "keywords": "Getty Museum collections, artworks, art works, art history, video, interpretation of art, acquisitions, artists, Getty art, collections Getty, collezioni Getty, colecciones Getty, Sammlung Getty, Getty exhibits, Getty current exhibitions, Getty Museum exhibits, los angeles collections, antiquities, decorative arts, sculpture, manuscripts, photography, paintings, drawings",
    "maker": "Agostino Carracci",
    "medium": "Black chalk with white chalk highlights on blue paper (recto); black chalk on blue paper (verso)",
    "name": "Kneeling Figure (recto); Reclining Figure (verso)",
    "object_number": "91.GB.68",
    "object_type": "Drawing",
    "on_view": "no",
    "open_content": "yes",
    "place_created": "Italy",
    "thumbimage": "http://www.getty.edu/museum/media/images/web/thumbnail/00036901.jpg",
    "title": "Kneeling Figure (recto); Reclining Figure (verso)"
}