{
    "canonical_url": "http://www.getty.edu/art/collection/objects/42879",
    "date": "about 1863",
    "description": "View of the Porta Ostiensis with the Pyramid of Caius Cestius; Altobelli & Molins (Italian, active until 1865); Rome, Italy; about 1863; Albumen silver print; 26.5 × 36.1 cm (10 7/16 × 14 3/16 in.); 84.XP.709.784; J. Paul Getty Museum, Los Angeles, California",
    "dimensions": "26.5 × 36.1 cm (10 7/16 × 14 3/16 in.)",
    "keywords": "Getty Museum collections, artworks, art works, art history, video, interpretation of art, acquisitions, artists, Getty art, collections Getty, collezioni Getty, colecciones Getty, Sammlung Getty, Getty exhibits, Getty current exhibitions, Getty Museum exhibits, los angeles collections, antiquities, decorative arts, sculpture, manuscripts, photography, paintings, drawings",
    "maker": "Altobelli & Molins",
    "medium": "Albumen silver print",
    "name": "View of the Porta Ostiensis with the Pyramid of Caius Cestius",
    "object_number": "84.XP.709.784",
    "object_type": "Print",
    "on_view": "no",
    "open_content": "no",
    "place_created": "Rome, Italy",
    "title": "View of the Porta Ostiensis with the Pyramid of Caius Cestius"
}